{
    "Interface & Direction": [
        "e600@plus",
        "e601@plus-circle",
        "e602@plus-square",
        "e603@minus",
        "e604@minus-circle",
        "e605@minus-square",
        "e606@check",
        "e607@check-circle",
        "e608@check-square",
        "e609@close",
        "e60a@close-circle",
        "e60b@close-square",
        "e60c@angle-left",
        "e60d@left-circle",
        "e60e@left-square",
        "e60f@angle-right",
        "e610@right-circle",
        "e611@right-square",
        "e612@angle-up",
        "e613@up-circle",
        "e614@up-square",
        "e615@angle-down",
        "e616@down-circle",
        "e617@down-square",
        "e618@arrow-left",
        "e619@arrow-right",
        "e61a@arrow-up",
        "e61b@arrow-down",
        "e61c@angle-double-left",
        "e61d@angle-double-right",
        "e61e@angle-double-up",
        "e61f@angle-double-down",
        "e620@caret-left",
        "e621@caret-left-circle",
        "e622@caret-left-square",
        "e623@caret-right",
        "e624@caret-right-circle",
        "e625@caret-right-square",
        "e626@caret-up",
        "e627@caret-up-circle",
        "e628@caret-up-square",
        "e629@caret-down",
        "e62a@caret-down-circle",
        "e62b@caret-down-square",
        "e62c@arrows",
        "e62d@arrows-alt",
        "e62e@expand-square",
        "e62f@compress-square",
        "e630@arrows-h",
        "e631@arrows-v",
        "e632@expand",
        "e633@compress",
        "e634@refresh",
        "e635@power-off",
        "e636@alt",
        "e637@command",
        "e638@esc",
        "e639@eye",
        "e63a@toggle",
        "e63b@toggle-off",
        "e63c@toggle-on",
        "e63d@spinner",
        "e63e@ellipsis-h"
    ],
    "Transfers & Share": [
        "e63f@download-circle",
        "e640@upload-circle",
        "e641@download",
        "e642@upload",
        "e643@download-disk",
        "e644@upload-disk",
        "e645@archive",
        "e646@download-my",
        "e647@download-bottom",
        "e648@download-caret",
        "e649@cloud",
        "e64a@cloud-upload",
        "e64b@cloud-download",
        "e64c@upload-square",
        "e64d@download-square",
        "e64e@share",
        "e64f@share-l",
        "e650@share-alt",
        "e651@share-arrow-alt",
        "e652@cloud-plus",
        "e653@cloud-minus",
        "e654@external-share",
        "e655@external-link",
        "e656@flag",
        "e657@flag-line",
        "e658@notice",
        "e659@announce",
        "e65a@rss-square",
        "e65b@code-fork",
        "e65c@Sitemap",
        "e65d@wifi-tower",
        "e65e@wifi",
        "e65f@signal-circle",
        "e660@Antenna",
        "e661@marquee-add",
        "e662@marquee-remove",
        "e663@exchange",
        "e664@repeat",
        "e665@share-arrow-alt2"
    ],
    "Edition, Design & Setting": [
        "e666@scissors",
        "e667@pen",
        "e668@pencil",
        "e669@circle",
        "e66a@slash-circle",
        "e66b@magnifier-expand",
        "e66c@magnifier-reduce",
        "e66d@magnifier",
        "e66e@pin",
        "e66f@clip",
        "e670@key",
        "e671@key-classic",
        "e672@wastebasket",
        "e673@eyes",
        "e674@eye-slash",
        "e675@slip-tongs",
        "e676@lock",
        "e677@unlock",
        "e678@calculator",
        "e679@target",
        "e67a@pen-point",
        "e67b@pencil-point",
        "e67c@brush-point",
        "e67d@magnet",
        "e67e@cube",
        "e67f@brush",
        "e680@type",
        "e681@paint-bucket",
        "e682@crop",
        "e683@marquee",
        "e684@color",
        "e685@ruler",
        "e686@ruler-triangle",
        "e687@magic",
        "e688@eyedropper",
        "e689@canvas",
        "e68a@tool",
        "e68b@repair"
    ],
    "Text, Alignment & Arrangement": [
        "e68c@align-justify",
        "e68d@align-left",
        "e68e@align-center",
        "e68f@align-right",
        "e690@layout-full",
        "e691@layout-side-left",
        "e692@layout-side-right",
        "e693@layout-left-two",
        "e694@layout-side-center",
        "e695@layout-side-three",
        "e696@layout-grid",
        "e697@layout-top",
        "e698@layout-top-left",
        "e699@layout-top-grid",
        "e69a@layout-top-colum",
        "e69b@layout-top-center",
        "e69c@layout-top-left-mid",
        "e69d@layout-top-right",
        "e69e@bold",
        "e69f@underline",
        "e6a0@italic",
        "e6a1@Caps",
        "e6a2@strikethrough",
        "e6a3@paragraph",
        "e6a4@list-ul",
        "e6a5@list-ul-square",
        "e6a6@list-ol",
        "e6a7@list-ul-l",
        "e6a8@indent",
        "e6a9@indent-arrow",
        "e6aa@dedent",
        "e6ab@dedent-arrow",
        "e6ac@link",
        "e6ad@link-l",
        "e6ae@unlink",
        "e6af@link-clip",
        "e6b0@content-right",
        "e6b1@content-left",
        "e6b2@content-grid",
        "e6b3@eraser",
        "e6b4@lineheight-plus",
        "e6b5@lineheight-minus",
        "e6b6@lineheight",
        "e6b7@code",
        "e6b8@rotate-right",
        "e6b9@rotate-left",
        "e6ba@stack-paper",
        "e6bb@paper"
    ],
    "Users": [
        "e6bc@user",
        "e6bd@user-plus",
        "e6be@user-minus",
        "e6bf@user-check",
        "e6c0@users",
        "e6c1@user-info",
        "e6c2@user-add",
        "e6c3@user-circle",
        "e6c4@user-folder",
        "e6c5@user-address",
        "e6c6@user-lock",
        "e6c7@female",
        "e6c8@male",
        "e6c9@gender",
        "e6ca@man",
        "e6cb@community"
    ],
    "Email, Chat & Comment": [
        "e6cc@email",
        "e6cd@mail-envelope",
        "e6ce@mail-card",
        "e6cf@mail-postcard",
        "e6d0@mail-open",
        "e6d1@mail-open-letter",
        "e6d2@mail-at",
        "e6d3@postbox",
        "e6d4@mail-reply",
        "e6d5@send",
        "e6d6@attach",
        "e6d7@mail-refresh",
        "e6d8@message-bubble",
        "e6d9@message-left",
        "e6da@message-right",
        "e6db@message-left-list",
        "e6dc@message-left-ellipsis",
        "e6dd@comment-list",
        "e6de@comment-bubble",
        "e6df@comment-double"
    ],
    "Status, Alert & Information": [
        "e6e0@status-check",
        "e6e1@status-check-box",
        "e6e2@status-check-boxout",
        "e6e3@status-check-circle",
        "e6e4@status-check-circleout",
        "e6e5@status-check-shield",
        "e6e6@status-check-shieldout",
        "e6e7@status-check-commentout",
        "e6e8@status-check-comment",
        "e6e9@status-check-home",
        "e6ea@status-check-homeout",
        "e6eb@ban",
        "e6ec@ban-square",
        "e6ed@ban-circle",
        "e6ee@ban-octagonal",
        "e6ef@ban-briefcase",
        "e6f0@unknown-square",
        "e6f1@unknown-circle",
        "e6f2@ok-square",
        "e6f3@ok-circle",
        "e6f4@ban-l",
        "e6f5@rollback",
        "e6f6@rollback-circle",
        "e6f7@exclamation-circle",
        "e6f8@exclamation-triangle",
        "e6f9@exclamation-octagon",
        "e6fa@information-circle",
        "e6fb@help-circle",
        "e6fc@skull"
    ],
    "Photo, Video & Audio": [
        "e6fd@image",
        "e6fe@images",
        "e6ff@photo",
        "e700@photo-camera-a",
        "e701@photo-camera-b",
        "e702@photo-camera-c",
        "e703@photo-camera-retro",
        "e704@photo-cameracorder",
        "e705@backward-arrow",
        "e706@forward-arrow",
        "e707@backward-double-arrow",
        "e708@forward-double-arrow",
        "e709@stop",
        "e70a@backward-double-circle",
        "e70b@forward-double-circle",
        "e70c@forward-double-circle2",
        "e70d@backward-double-circle2",
        "e70e@backward-end-circle",
        "e70f@forward-end-circle",
        "e710@backward-end-double-circle",
        "e711@forward-end-double-circle",
        "e712@stop-circle",
        "e713@play-circle",
        "e714@backward-double-square",
        "e715@forward-double-square",
        "e716@backward-end-square",
        "e717@forward-end-square",
        "e718@backward-end-double-square",
        "e719@forward-end-double-square",
        "e71a@stop-square",
        "e71b@play-square",
        "e71c@record",
        "e71d@play",
        "e71f@forward-double-angle",
        "e720@backward-double-angle",
        "e721@pause",
        "e722@forward-end-angle",
        "e723@backward-end-angle",
        "e724@h-41",
        "e725@record-circle",
        "e726@forward-double-circle-o",
        "e727@backward-double-circle-o",
        "e728@pause-circle-o",
        "e729@pausenow-circle-o",
        "e72a@video",
        "e72b@play-movie",
        "e72c@play-tv",
        "e72d@play-tv-wide",
        "e72e@video-recoder",
        "e72f@play-film",
        "e730@film",
        "e731@sound-max",
        "e732@sound-mid",
        "e733@sound-min",
        "e734@sound-plus",
        "e735@sound-minus",
        "e736@sound-off",
        "e737@sound-close",
        "e738@volume-circle",
        "e739@volume-off-circle",
        "e73a@volume-max",
        "e73b@volume-mid",
        "e73c@volume-min",
        "e73d@volume-plus",
        "e73e@volume-minus",
        "e73f@volume-off",
        "e740@volume-close",
        "e741@headset",
        "e742@mic",
        "e743@mic-off",
        "e744@microphone",
        "e745@mic-new",
        "e746@volume-bar",
        "e747@record-play",
        "e748@mix-machine",
        "e749@music-note-a",
        "e74a@music-note-b",
        "e74b@music-note-c",
        "e74c@speaker",
        "e74d@keyboard",
        "e74e@saxophone",
        "e74f@music-scale"
    ],
    "Vote, Rewards & Tag": [
        "e750@star",
        "e751@medal",
        "e752@medal-l",
        "e753@trophy",
        "e754@love-o",
        "e755@present",
        "e756@flag-triangle",
        "e757@tag-a",
        "e758@tag-left",
        "e759@tags",
        "e75a@tag-thin",
        "e75b@tag-lefts",
        "e75c@heart",
        "e75d@marker-pin",
        "e75e@marker-point",
        "e75f@tag-plus",
        "e760@bookmark",
        "e761@bookmark-left",
        "e762@bookmark-spread"
    ],
    "Map, Location & Transportation": [
        "e763@marker-circle",
        "e764@marker-plus",
        "e765@marker-minus",
        "e766@marker-multiply",
        "e767@marker-circle-round",
        "e768@marker-plus-round",
        "e769@marker-minus-round",
        "e76a@marker-multiply-round",
        "e76b@marker-circle-fat",
        "e76c@marker-plus-fat",
        "e76d@marker-minus-fat",
        "e76e@marker-multiply-fat",
        "e76f@map-marker",
        "e770@map-folding",
        "e771@location-arrow",
        "e772@compass-a",
        "e773@compass-b",
        "e774@crosshairs",
        "e775@flag-wind",
        "e776@car",
        "e777@taxi",
        "e778@plane"
    ],
    "Device & Hardware": [
        "e779@monitor-mac",
        "e77a@monitor",
        "e77b@laptop",
        "e77c@mouse",
        "e77d@mouse-wheel",
        "e71e@print-paper",
        "e77f@mobile",
        "e780@mobile-phone",
        "e781@tablet",
        "e782@battery-full",
        "e783@battery-mid",
        "e784@battery-min",
        "e785@battery-non",
        "e786@disk-old",
        "e787@usb",
        "e788@memorycard",
        "e789@cd-r",
        "e78a@hdd",
        "e78b@hardware-wifi",
        "e78c@calculators",
        "e78d@plug",
        "e78e@gamepad",
        "e78f@gamepad-simple"
    ],
    "Time & Schedule": [
        "e790@time-o",
        "e791@time-point",
        "e792@clock",
        "e793@timer",
        "e794@time-forward",
        "e795@time-back",
        "e796@time-hour",
        "e797@alarm-clock",
        "e798@bell",
        "e799@bell-ring",
        "e79a@bell-mute",
        "e79b@sandwatch",
        "e79c@sandwatch-forward",
        "e79d@watch",
        "e79e@time-day",
        "e79f@time-night",
        "e7a0@calendars",
        "e7a1@calendars-month",
        "e7a2@calendars-week",
        "e7a3@calendars-time",
        "e7a4@calendars-add",
        "e7a5@calendars-remove",
        "e7a6@calendars-delete",
        "e7a7@calendars-check"
    ],
    "File & Folder": [
        "e7a8@file",
        "e7a9@file-add",
        "e7aa@file-remove",
        "e7ab@file-text",
        "e7ac@documents",
        "e7ad@documents-twin",
        "e7ae@file-image",
        "e7af@file-movie",
        "e7b0@file-check",
        "e7b1@file-music",
        "e7b2@file-code",
        "e7b3@file-zip",
        "e7b4@file-excel",
        "e7b5@file-word",
        "e7b6@file-powerpoint",
        "e7b7@file-time",
        "e7b8@file-check-o",
        "e7b9@file-add-o",
        "e7ba@file-remove-o",
        "e7bb@file-upload-o",
        "e7bc@file-download-o",
        "e7bd@file-bookmark",
        "e7be@file-lock",
        "e7bf@folder",
        "e7c0@folder-open",
        "e7c1@folder-add",
        "e7c2@folder-check",
        "e7c3@folder-remove",
        "e7c4@folder-delete",
        "e7c5@folder-upload",
        "e7c6@folder-download",
        "e7c7@folder-bookmark",
        "e7c8@folder-lock",
        "e7c9@folder-time",
        "e7ca@folder-music",
        "e7cb@folder-image",
        "e7cc@folder-movie",
        "e7cd@folder-code",
        "e7ce@folder-zip"
    ],
    "Windows & Server": [
        "e7cf@windows",
        "e7d0@windows-text",
        "e7d1@windows-forbidden",
        "e7d2@windows-time",
        "e7d3@windows-add",
        "e7d4@windows-remove",
        "e7d5@windows-delete",
        "e7d6@windows-check",
        "e7d7@windows-download",
        "e7d8@windows-upload",
        "e7d9@windows-lock",
        "e7da@windows-forward",
        "e7db@windows-refresh",
        "e7dc@windows-home",
        "e7dd@windows-favorite",
        "e7de@windows-look",
        "e7df@server",
        "e7e0@server-folder",
        "e7e1@server-hardware",
        "e7e2@server-forbidden",
        "e7e3@server-time",
        "e7e4@server-add",
        "e7e5@server-remove",
        "e7e6@server-delete",
        "e7e7@server-check",
        "e7e8@server-download",
        "e7e9@server-upload",
        "e7ea@server-lock",
        "e7eb@server-forward",
        "e7ec@server-refresh",
        "e7ed@server-look"
    ],
    "Programming & Charts": [
        "e7ee@html5",
        "e7ef@css3",
        "e7f0@ruby",
        "e7f1@radiation",
        "e7f2@rocket",
        "e7f3@atom",
        "e7f4@shield-o",
        "e7f5@saturn",
        "e7f6@globus",
        "e7f7@funnel",
        "e7f8@chart-line",
        "e7f9@chart-bar",
        "e7fa@chart-area",
        "e7fb@chart-wave"
    ],
    "Social": [
        "e819@facebook",
        "e81a@google-plus",
        "e81b@twitter",
        "e81c@vk",
        "e81d@blogger",
        "e81e@hubpages",
        "e81f@medium",
        "e820@naver",
        "e821@tumblr",
        "e822@xing",
        "e823@bloglovin",
        "e824@stumbleupon",
        "e825@delicious",
        "e826@linkedin",
        "e827@pocket",
        "e828@feedly",
        "e829@social-rssfeed",
        "e82a@digg",
        "e82b@reddit",
        "e82c@social-email",
        "e82d@social-print",
        "e82e@github",
        "e82f@git",
        "e830@hunie",
        "e831@trello",
        "e832@yobi",
        "e833@skillshare",
        "e834@slideshare",
        "e835@stackoverflow",
        "e836@flickr",
        "e837@instagram",
        "e838@kakaostory",
        "e839@path",
        "e83a@behance",
        "e83b@deviantart",
        "e83c@dribbble",
        "e83d@pinterest",
        "e83e@evernote",
        "e83f@onenote",
        "e840@goodreads",
        "e841@kickstarter",
        "e842@senscritique",
        "e843@myplace",
        "e844@soundcloud",
        "e845@vimeo",
        "e846@youtube",
        "e847@foursquare",
        "e848@trover",
        "e849@facebook-messenger",
        "e84a@kakaotalk",
        "e84b@line-messenger",
        "e84c@skype",
        "e84d@telegram",
        "e84e@wechat",
        "e84f@whatsapp",
        "e850@bitrix",
        "e851@concrete5",
        "e852@dot-cms",
        "e853@drupal",
        "e854@expressionengine",
        "e855@ghost",
        "e856@joomla",
        "e857@kimsq",
        "e858@magento",
        "e859@opencart",
        "e85a@oscommerce",
        "e85b@prestashop",
        "e85c@silverstripe",
        "e85d@typo3",
        "e85e@ubercart",
        "e85f@vbulletin",
        "e860@wix",
        "e861@virtuemart",
        "e862@wordpress",
        "e863@xpressengine",
        "e864@zencart"
    ],
    "etc": [
        "e7fc@cocktail",
        "e7fd@icecream",
        "e7fe@fork",
        "e7ff@spoon",
        "e800@knife",
        "e801@burger",
        "e802@rice",
        "e803@cup",
        "e804@lemon",
        "e805@orange",
        "e806@watermelon",
        "e807@cake",
        "e808@pill",
        "e809@glasses",
        "e80a@umbrella",
        "e80b@bomb",
        "e80c@bonfire",
        "e80d@tent",
        "e80e@handbag",
        "e80f@briefcase-l",
        "e810@credit-card",
        "e811@taxi-square",
        "e812@idea",
        "e813@telephone",
        "e814@book-spread",
        "e815@evergreens",
        "e816@carts",
        "e817@tree",
        "e818@leaf"
    ]
}
